bank_statement_separator/__init__.py
bank_statement_separator/config.py
bank_statement_separator/main.py
bank_statement_separator/workflow.py
bank_statement_separator-3.0.5.dist-info/licenses/LICENSE
bank_statement_separator-3.0.5.dist-info/METADATA
bank_statement_separator-3.0.5.dist-info/WHEEL
bank_statement_separator-3.0.5.dist-info/entry_points.txt
bank_statement_separator-3.0.5.dist-info/top_level.txt
bank_statement_separator-3.0.5.dist-info/RECORD
