Metadata-Version: 2.4
Name: bank-statement-separator
Version: 3.0.5
Summary: AI-powered tool for separating multi-statement PDF files using LangChain and LangGraph
Author-email: Stephen Eaton <seaton@strobotics.com.au>
Maintainer-email: Stephen Eaton <seaton@strobotics.com.au>
License-Expression: MIT
Project-URL: Homepage, https://github.com/madeinoz67/bank-statement-separator
Project-URL: Documentation, https://madeinoz67.github.io/bank-statement-separator/
Project-URL: Repository, https://github.com/madeinoz67/bank-statement-separator
Project-URL: Issues, https://github.com/madeinoz67/bank-statement-separator/issues
Project-URL: Changelog, https://github.com/madeinoz67/bank-statement-separator/blob/main/docs/release_notes/CHANGELOG.md
Keywords: pdf,ai,langchain,bank-statement,document-processing,automation,financial,machine-learning
Classifier: Development Status :: 4 - Beta
Classifier: Intended Audience :: Developers
Classifier: Intended Audience :: Financial and Insurance Industry
Classifier: Operating System :: OS Independent
Classifier: Programming Language :: Python :: 3
Classifier: Programming Language :: Python :: 3.11
Classifier: Programming Language :: Python :: 3.12
Classifier: Topic :: Office/Business :: Financial :: Accounting
Classifier: Topic :: Scientific/Engineering :: Artificial Intelligence
Classifier: Topic :: Utilities
Requires-Python: >=3.11
License-File: LICENSE
Requires-Dist: langgraph>=0.2.0
Requires-Dist: langchain>=0.3.0
Requires-Dist: langchain-openai>=0.2.0
Requires-Dist: pymupdf>=1.23.0
Requires-Dist: python-dotenv>=1.0.0
Requires-Dist: click>=8.0.0
Requires-Dist: pydantic>=2.0.0
Requires-Dist: rich>=13.0.0
Requires-Dist: faker>=37.6.0
Requires-Dist: reportlab>=4.4.3
Requires-Dist: httpx>=0.28.1
Requires-Dist: mkdocs-material>=9.6.18
Requires-Dist: mkdocs-mermaid2-plugin>=1.2.2
Requires-Dist: langchain-ollama>=0.3.7
Provides-Extra: dev
Requires-Dist: pytest>=7.0.0; extra == "dev"
Requires-Dist: pytest-asyncio>=0.21.0; extra == "dev"
Requires-Dist: black>=23.0.0; extra == "dev"
Requires-Dist: ruff>=0.1.0; extra == "dev"
Requires-Dist: mypy>=1.0.0; extra == "dev"
Dynamic: license-file
